agent_search/__init__.py
agent_search/app/server.py
agent_search/core/__init__.py
agent_search/core/client.py
agent_search/core/search_types.py
agent_search/core/utils.py
agent_search/providers/__init__.py
agent_search/providers/sciphi.py
agent_search/scripts/populate_qdrant_from_postgres.py
agent_search/scripts/run_rag.py
agent_search/scripts/run_search.py
agent_search/search/__init__.py
agent_search/search/base.py
agent_search-0.1.0.dist-info/LICENSE
agent_search-0.1.0.dist-info/METADATA
agent_search-0.1.0.dist-info/WHEEL
agent_search-0.1.0.dist-info/RECORD
