Metadata-Version: 2.1
Name: agent_search
Version: 0.1.0
Summary: AgentSearch: An open source framework and dataset for webscale local search.
License: Apache-2.0
Author: Owen Colegrove
Author-email: owen@sciphi.ai
Requires-Python: >=3.9,<3.12
Classifier: License :: OSI Approved :: Apache Software License
Classifier: Programming Language :: Python :: 3
Classifier: Programming Language :: Python :: 3.9
Classifier: Programming Language :: Python :: 3.10
Classifier: Programming Language :: Python :: 3.11
Requires-Dist: configparser (>=5.0.0,<6.0.0)
Requires-Dist: fire (>=0.5.0,<0.6.0)
Requires-Dist: numpy (>=1.25.2,<2.0.0)
Requires-Dist: openai (==0.27.8)
Requires-Dist: pydantic (>=1.10.13,<2.0.0)
Requires-Dist: qdrant_client (>=1.7.0,<2.0.0)
Requires-Dist: requests (>=2.31.0,<3.0.0)
Requires-Dist: sciphi_synthesizer (==1.0.5)
Requires-Dist: transformers (>=4.33.1,<5.0.0)
